prompting/__init__.py
prompting/engine.py
prompting/magics.py
prompting/manager.py
prompting/memory.py
prompting/tasks.py
prompting/prompts/__init__.py
prompting/prompts/meta_prompt.txt
prompting/prompts/system_prompt.txt
prompting-0.1.0.dist-info/LICENSE
prompting-0.1.0.dist-info/METADATA
prompting-0.1.0.dist-info/WHEEL
prompting-0.1.0.dist-info/top_level.txt
prompting-0.1.0.dist-info/RECORD
