Metadata-Version: 2.1
Name: prompting
Version: 0.1.0
Summary: This module provides iPython integration and magics that allow prompting.
Home-page: https://gitlab.com/mcaledonensis/magickey/-/tree/prompting
Author: Merlinus Caledonensis
Author-email: merlin@roundtable.game
License: Apache 2.0
License-File: LICENSE
Requires-Dist: openai
Requires-Dist: parsimonious
